rose_pine_jupyterlab/__init__.py
rose_pine_jupyterlab/_version.py
rose_pine_jupyterlab-0.2.1.data/data/share/jupyter/labextensions/rose_pine_jupyterlab/package.json
rose_pine_jupyterlab-0.2.1.data/data/share/jupyter/labextensions/rose_pine_jupyterlab/static/158.1cd74af599501baea854.js
rose_pine_jupyterlab-0.2.1.data/data/share/jupyter/labextensions/rose_pine_jupyterlab/static/remoteEntry.234a97a08824505fc307.js
rose_pine_jupyterlab-0.2.1.data/data/share/jupyter/labextensions/rose_pine_jupyterlab/static/style.js
rose_pine_jupyterlab-0.2.1.data/data/share/jupyter/labextensions/rose_pine_jupyterlab/static/third-party-licenses.json
rose_pine_jupyterlab-0.2.1.data/data/share/jupyter/labextensions/rose_pine_jupyterlab/themes/rose_pine_jupyterlab/index.css
rose_pine_jupyterlab-0.2.1.data/data/share/jupyter/labextensions/rose_pine_jupyterlab/themes/rose_pine_jupyterlab/index.js
rose_pine_jupyterlab-0.2.1.data/data/share/jupyter/labextensions/rose_pine_jupyterlab/install.json
rose_pine_jupyterlab-0.2.1.dist-info/METADATA
rose_pine_jupyterlab-0.2.1.dist-info/WHEEL
rose_pine_jupyterlab-0.2.1.dist-info/RECORD
