Metadata-Version: 2.4
Name: rose_pine_jupyterlab
Version: 0.2.1
Summary: Soho Vibes for JupyterLab
Project-URL: Homepage, https://github.com/aaravind100/jupyterlab
Project-URL: Bug Tracker, https://github.com/aaravind100/jupyterlab/issues
Project-URL: Repository, https://github.com/aaravind100/jupyterlab.git
Author-email: Ajith Aravind <ajith.aravind100@gmail.com>
License: BSD 3-Clause License
Keywords: jupyter,jupyterlab,jupyterlab-extension
Classifier: Framework :: Jupyter
Classifier: Framework :: Jupyter :: JupyterLab
Classifier: Framework :: Jupyter :: JupyterLab :: 4
Classifier: Framework :: Jupyter :: JupyterLab :: Extensions
Classifier: Framework :: Jupyter :: JupyterLab :: Extensions :: Prebuilt
Classifier: Framework :: Jupyter :: JupyterLab :: Extensions :: Themes
Classifier: License :: OSI Approved :: BSD License
Classifier: Programming Language :: Python
Classifier: Programming Language :: Python :: 3
Classifier: Programming Language :: Python :: 3.9
Classifier: Programming Language :: Python :: 3.10
Classifier: Programming Language :: Python :: 3.11
Classifier: Programming Language :: Python :: 3.12
Classifier: Programming Language :: Python :: 3.13
Requires-Python: >=3.9
